{
  "cli": {
    "version": ">= 15.0.0",
    "appVersionSource": "remote"
  },
  "build": {
    "development": {
      "developmentClient": true,
      "distribution": "internal",
      "android": {
        "gradleCommand": ":app:assembleDebug"
      },
      "ios": {
        "buildConfiguration": "Debug"
      }
    },
    "preview": {
      "distribution": "internal",
      "android": {
        "buildType": "apk"
      },
      "ios": {
        "simulator": true
      },
      "env": {
        "EXPO_PUBLIC_API_BASE_URL": "https://api.alhilaltravels.com/api/v1/"
      }
    },
    "production": {
      "android": {
        "buildType": "app-bundle"
      },
      "ios": {
        "buildConfiguration": "Release"
      },
      "env": {
        "EXPO_PUBLIC_API_BASE_URL": "https://api.alhilaltravels.com/api/v1/"
      }
    },
    "production-apk": {
      "extends": "production",
      "android": {
        "buildType": "apk"
      }
    }
  },
  "submit": {
    "production": {}
  }
}

